{
  "highRiskStatisticMethod": "PERCENT",
  "highRiskStatisticPeriod": "MONTH",
  "lazyLoad": true,
  "owner": "Administrator",
  "priority": "0",
  "processingType": "WORKFLOW",
  "statisticMethod": "AVERAGE",
  "statisticPeriod": "MONTH",
  "workflowType": "STANDARD",
  "customFieldValues": {
  },
  "items": 
  [
    {
      "highRiskStatisticMethod": "PERCENT",
      "highRiskStatisticPeriod": "MONTH",
      "name": "WORKFLOW_LEVEL_STOCK",
      "processingTemplate": "WORKFLOW_LEVEL_STOCK",
      "statisticMethod": "AVERAGE",
      "statisticPeriod": "MONTH"
    },
    {
      "highRiskStatisticMethod": "PERCENT",
      "highRiskStatisticPeriod": "MONTH",
      "name": "WORKFLOW_LEVEL_STOCK_1",
      "processingTemplate": "WORKFLOW_LEVEL_STOCK_1",
      "statisticMethod": "AVERAGE",
      "statisticPeriod": "MONTH"
    },
    {
      "highRiskStatisticMethod": "PERCENT",
      "highRiskStatisticPeriod": "MONTH",
      "name": "WORKFLOW_LEVEL_STOCK_2",
      "processingTemplate": "WORKFLOW_LEVEL_STOCK_2",
      "statisticMethod": "AVERAGE",
      "statisticPeriod": "MONTH"
    },
    {
      "highRiskStatisticMethod": "PERCENT",
      "highRiskStatisticPeriod": "MONTH",
      "name": "WORKFLOW_LEVEL_STOCK_3",
      "processingTemplate": "WORKFLOW_LEVEL_STOCK_3",
      "statisticMethod": "AVERAGE",
      "statisticPeriod": "MONTH"
    },
    {
      "highRiskStatisticMethod": "PERCENT",
      "highRiskStatisticPeriod": "MONTH",
      "name": "WORKFLOW_LEVEL_STOCK_4",
      "processingTemplate": "WORKFLOW_LEVEL_STOCK_4",
      "statisticMethod": "AVERAGE",
      "statisticPeriod": "MONTH"
    },
    {
      "highRiskStatisticMethod": "PERCENT",
      "highRiskStatisticPeriod": "MONTH",
      "name": "000_IMPORT_TEST_TASK_001",
      "processingTemplate": "000_IMPORT_TEST_TASK_001",
      "statisticMethod": "AVERAGE",
      "statisticPeriod": "MONTH",
      "dependencies": 
      [
        {
          "dependencyType": "PREDECESSOR",
          "name": "WORKFLOW_LEVEL_STOCK_4",
          "predecessor": "WORKFLOW_LEVEL_STOCK_4",
          "processingStatus": "COMPLETED",
          "processingType": "WORKFLOW",
          "workflowType": "STANDARD"
        }
      ]
    }
  ]
}